grohe/__init__.py
grohe/client.py
grohe/tokens.py
grohe/dto/grohe_device.py
grohe/dto/grohe_dto.py
grohe/enum/grohe_enum.py
grohe-0.2.4.dist-info/licenses/LICENSE
grohe-0.2.4.dist-info/METADATA
grohe-0.2.4.dist-info/WHEEL
grohe-0.2.4.dist-info/top_level.txt
grohe-0.2.4.dist-info/RECORD
