Metadata-Version: 2.4
Name: grohe
Version: 0.2.4
Summary: A python package to interact with the Grohe API.
Author-email: Konstantin Weber <konstantin@koproductions.dev>, Flo Schilli <github.contact@flo.schilli.dev>
License: MIT License
Project-URL: Homepage, https://github.com/koproductions-code/grohe
Project-URL: Documentation, https://github.com/koproductions-code/grohe/wiki/
License-File: LICENSE
Requires-Dist: bs4==0.0.2
Requires-Dist: httpx>=0.27.0
Dynamic: license-file
